[{"coordinates": [57.315, 21.01333], "name": "Sayh al Uhaymir 315", "class": "H6", "mass": "6", "year": 2004}, {"coordinates": [159.75, -79.68333], "name": "Meteorite Hills 01205", "class": "LL5", "mass": "13.2", "year": 2001}, {"coordinates": [155.75, -79.68333], "name": "Meteorite Hills 00425", "class": "Diogenite", "mass": "118.3", "year": 2000}, {"coordinates": [16.18333, 27.35], "name": "Dar al Gani 915", "class": "Howardite", "mass": "740", "year": 2000}, {"coordinates": [160.46161, -72.95244], "name": "Frontier Mountain 03054", "class": "L6", "mass": "0.94", "year": 2003}, {"coordinates": [159.75, -79.68333], "name": "Meteorite Hills 01244", "class": "Acapulcoite", "mass": "76.5", "year": 2001}, {"coordinates": [54.7253, 18.92618], "name": "Dhofar 1642", "class": "H6", "mass": "1540", "year": 2009}, {"coordinates": [54.47493, 18.9108], "name": "Dhofar 451", "class": "L6", "mass": "745", "year": 2001}, {"coordinates": [56.666, 19.51878], "name": "Jiddat al Harasis 646", "class": "H4", "mass": "3020", "year": 2010}, {"coordinates": [-69.71667, -25.23333], "name": "Catalina 002", "class": "LL3", "mass": "61.1", "year": 2010}, {"coordinates": [159.75, -79.68333], "name": "Meteorite Hills 01157", "class": "L5", "mass": "3.8", "year": 2001}, {"coordinates": [54.52335, 19.37243], "name": "Dhofar 1679", "class": "H4", "mass": "184.3", "year": 2011}, {"coordinates": [75.34194, -72.77306], "name": "Grove Mountains 021953", "class": "H6", "mass": "3.26", "year": 2003}, {"coordinates": [75.24417, -72.9975], "name": "Grove Mountains 024064", "class": "H5 ", "mass": "8.83", "year": 2003}, {"coordinates": [75.34083, -72.775], "name": "Grove Mountains 022488", "class": "H5", "mass": "0.55", "year": 2003}, {"coordinates": [54.425, 18.25167], "name": "Dhofar 714", "class": "H5", "mass": "207", "year": 2000}, {"coordinates": [56.08783, 20.6322], "name": "Ramlat as Sahmah 207", "class": "L6", "mass": "202.01", "year": 2003}, {"coordinates": [16.05, 27.38333], "name": "Dar al Gani 939", "class": "L6", "mass": "367", "year": 2000}, {"coordinates": [159.75, -79.68333], "name": "Meteorite Hills 01041", "class": "L5", "mass": "198.6", "year": 2001}, {"coordinates": [155.75, -79.68333], "name": "Meteorite Hills 00466", "class": "LL5", "mass": "296.8", "year": 2000}, {"coordinates": [56.4297, 19.60597], "name": "Jiddat al Harasis 441", "class": "L4", "mass": "513.83100000000002", "year": 2007}, {"coordinates": [75.32472, -72.77444], "name": "Grove Mountains 023117", "class": "L6", "mass": "1.31", "year": 2003}, {"coordinates": [159.75, -79.68333], "name": "Meteorite Hills 01292", "class": "LL6", "mass": "7.8", "year": 2001}, {"coordinates": [54.81357, 19.11453], "name": "Dhofar 1703", "class": "H6", "mass": "193", "year": 2010}, {"coordinates": [160.5, -84.21667], "name": "MacAlpine Hills 02703", "class": "Howardite", "mass": "19.3", "year": 2002}, {"coordinates": [54.6369, 18.95435], "name": "Dhofar 1721", "class": "H5", "mass": "238", "year": 2010}, {"coordinates": [55.45073, 18.86795], "name": "Shalim 008", "class": "H5", "mass": "323.5", "year": 2009}, {"coordinates": [56.43172, 19.60792], "name": "Jiddat al Harasis 446", "class": "L4", "mass": "210.578", "year": 2007}, {"coordinates": [-11.13158, 28.00247], "name": "Northwest Africa 6963", "class": "Martian (shergottite)", "mass": "8000", "year": 2011}, {"coordinates": [56.83205, 19.46162], "name": "Jiddat al Harasis 097", "class": "L5", "mass": "674.3", "year": 2002}, {"coordinates": [75.10242, -72.91086], "name": "Grove Mountains 090297", "class": "L4", "mass": "14.73", "year": 2010}, {"coordinates": [54.92133, 19.2195], "name": "Dhofar 1536", "class": "H6", "mass": "176", "year": 2006}, {"coordinates": [160.48508, -72.95285], "name": "Frontier Mountain 10097", "class": "LL3", "mass": "7.7", "year": 2011}, {"coordinates": [75.33, -72.78028], "name": "Grove Mountains 051889", "class": "L6", "mass": "19.079999999999998", "year": 2006}, {"coordinates": [54.63105, 18.93593], "name": "Dhofar 454", "class": "H5", "mass": "80", "year": 2001}, {"coordinates": [75.284, -72.77758], "name": "Grove Mountains 053986", "class": "L5", "mass": "1.74", "year": 2006}, {"coordinates": [54.16786, 19.37919], "name": "Dhofar 547", "class": "L5", "mass": "514", "year": 2001}, {"coordinates": [0.1, 25.28333], "name": "Tanezrouft 069", "class": "H5", "mass": "180", "year": 2002}, {"coordinates": [75.27861, -72.7825], "name": "Grove Mountains 022593", "class": "L6", "mass": "0.97", "year": 2003}, {"coordinates": [-117.62022, 39.68444], "name": "Tungsten Mountain 004", "class": "H6", "mass": "8.1", "year": 2001}, {"coordinates": [54.56667, 18.92667], "name": "Dhofar 1437", "class": "H5", "mass": "324", "year": 2003}, {"coordinates": [57.28345, 21.06722], "name": "Sayh al Uhaymir 200", "class": "L6", "mass": "16.079999999999998", "year": 2002}, {"coordinates": [75.32028, -72.77361], "name": "Grove Mountains 022329", "class": "H5", "mass": "0.48", "year": 2003}, {"coordinates": [13.43333, 58.58333], "name": "\u00d6sterplana 042", "class": "Relict OC", "mass": "", "year": 2000}, {"coordinates": [56.41405, 19.97973], "name": "Jiddat al Harasis 238", "class": "Mesosiderite", "mass": "298", "year": 2005}, {"coordinates": [-70, -86.36667], "name": "LaPaz Icefield 02237", "class": "H5", "mass": "24.4", "year": 2002}, {"coordinates": [75.28694, -72.78056], "name": "Grove Mountains 022663", "class": "H5", "mass": "0.68", "year": 2003}, {"coordinates": [56.56283, 20.12617], "name": "Sayh al Uhaymir 500", "class": "H6", "mass": "1269", "year": 2009}, {"coordinates": [56.48062, 19.99102], "name": "Jiddat al Harasis 257", "class": "H4-5", "mass": "331.9", "year": 2005}, {"coordinates": [75.31389, -72.77833], "name": "Grove Mountains 022282", "class": "L6", "mass": "43.3", "year": 2003}, {"coordinates": [54.71833, 19.125], "name": "Dhofar 1295", "class": "L/LL6", "mass": "30", "year": 2003}, {"coordinates": [159.75, -79.68333], "name": "Meteorite Hills 001040", "class": "L5", "mass": "43.3", "year": 2000}, {"coordinates": [56.40473, 20.0049], "name": "Ramlat as Sahmah 384", "class": "Mesosiderite-C2", "mass": "5026", "year": 2010}, {"coordinates": [159.75, -79.68333], "name": "Meteorite Hills 00548", "class": "L5", "mass": "89.7", "year": 2000}, {"coordinates": [10.21017, 30.74819], "name": "Tieret 001", "class": "H6", "mass": "602", "year": 2009}, {"coordinates": [75.2064, -72.9925], "name": "Grove Mountains 020214", "class": "H5", "mass": "1.28", "year": 2003}, {"coordinates": [-70, -86.36667], "name": "LaPaz Icefield 02244", "class": "LL5", "mass": "106.46", "year": 2002}, {"coordinates": [75.3375, -72.77528], "name": "Grove Mountains 052073", "class": "L6", "mass": "242", "year": 2006}, {"coordinates": [55.41193, 20.91903], "name": "Ramlat as Sahmah 322", "class": "H3", "mass": "264.39999999999998", "year": 2009}, {"coordinates": [10.8, 32.86667], "name": "Beni M'hira", "class": "L6", "mass": "19000", "year": 2001}, {"coordinates": [-5.08833, 30.63583], "name": "Northwest Africa 767", "class": "L4", "mass": "5146", "year": 2000}, {"coordinates": [75.30111, -72.78083], "name": "Grove Mountains 053579", "class": "L6", "mass": "3.85", "year": 2006}, {"coordinates": [75.31611, -72.77972], "name": "Grove Mountains 051708", "class": "L5", "mass": "6.5", "year": 2006}, {"coordinates": [75.24639, -72.98389], "name": "Grove Mountains 020339", "class": "L5", "mass": "0.64", "year": 2003}, {"coordinates": [75.30278, -72.78167], "name": "Grove Mountains 022171", "class": "L6", "mass": "73", "year": 2003}, {"coordinates": [54.56833, 19.34917], "name": "Dhofar 548", "class": "H4", "mass": "3677", "year": 2001}, {"coordinates": [75.35361, -72.77528], "name": "Grove Mountains 052833", "class": "L6", "mass": "1.56", "year": 2006}, {"coordinates": [160.5, -84.21667], "name": "MacAlpine Hills 02483", "class": "H4", "mass": "0.59", "year": 2002}, {"coordinates": [55.81017, 19.33183], "name": "Jiddat al Harasis 370", "class": "L~6", "mass": "1453.1", "year": 2003}, {"coordinates": [155.75, -79.68333], "name": "Meteorite Hills 00825", "class": "L5", "mass": "40.35", "year": 2000}, {"coordinates": [157, -83.25], "name": "Miller Range 03346", "class": "Martian (nakhlite)", "mass": "715.2", "year": 2003}, {"coordinates": [75.31861, -72.77833], "name": "Grove Mountains 052445", "class": "L6", "mass": "2.98", "year": 2006}, {"coordinates": [-110.43418, 31.96185], "name": "Whetstone Mountains", "class": "H5", "mass": "2138.7399999999998", "year": 2009}, {"coordinates": [75.32833, -72.77778], "name": "Grove Mountains 021878", "class": "H4", "mass": "1.3", "year": 2003}, {"coordinates": [155.75, -79.68333], "name": "Meteorite Hills 01086", "class": "Eucrite-unbr", "mass": "2.73", "year": 2001}, {"coordinates": [75.23889, -72.99917], "name": "Grove Mountains 020066", "class": "H4", "mass": "1.76", "year": 2003}, {"coordinates": [56.65228, 20.40702], "name": "Sayh al Uhaymir 522", "class": "L6", "mass": "977.8", "year": 2009}, {"coordinates": [75.2835, -72.78505], "name": "Grove Mountains 054065", "class": "H5", "mass": "1.31", "year": 2006}, {"coordinates": [75.33083, -72.77472], "name": "Grove Mountains 021806", "class": "L5", "mass": "58.6", "year": 2003}, {"coordinates": [56.64243, 19.70438], "name": "Jiddat al Harasis 219", "class": "L4-5", "mass": "376.89", "year": 2005}, {"coordinates": [54.65452, 18.88637], "name": "Dhofar 745", "class": "H4", "mass": "3600", "year": 2000}, {"coordinates": [54.25013, 18.34955], "name": "Dhofar 1462", "class": "L~4", "mass": "400.8", "year": 2008}, {"coordinates": [-0.51863, 24.58025], "name": "Tanezrouft 079", "class": "H6", "mass": "1031", "year": 2003}, {"coordinates": [55.89948, 19.36147], "name": "Jiddat al Harasis 385", "class": "L~6", "mass": "161.6", "year": 2003}, {"coordinates": [-70, -86.36667], "name": "LaPaz Icefield 02334", "class": "LL6", "mass": "135.09", "year": 2002}, {"coordinates": [-5.91667, 30.3], "name": "Northwest Africa 828", "class": "H3.0-3.4", "mass": "738", "year": 2000}, {"coordinates": [159.75, -79.68333], "name": "Meteorite Hills 00996", "class": "LL6", "mass": "11.4", "year": 2000}, {"coordinates": [159.75, -79.68333], "name": "Meteorite Hills 00989", "class": "L5", "mass": "36.1", "year": 2000}, {"coordinates": [57.31327, 21.0689], "name": "Sayh al Uhaymir 285", "class": "H5", "mass": "9.300000000000001", "year": 2004}, {"coordinates": [-69.86083, -25.44067], "name": "San Juan 061", "class": "L5", "mass": "1.3", "year": 2010}, {"coordinates": [-70.53333, -24.85], "name": "El M\u00e9dano 029", "class": "L5", "mass": "392", "year": 2010}, {"coordinates": [75.17944, -73.10417], "name": "Grove Mountains 020003", "class": "LL5", "mass": "4.76", "year": 2002}, {"coordinates": [56.4177, 19.98715], "name": "Jiddat al Harasis 206", "class": "Mesosiderite", "mass": "1185.51", "year": 2002}, {"coordinates": [16.36667, 27.08333], "name": "Dar al Gani 977", "class": "Ureilite", "mass": "17", "year": 2000}, {"coordinates": [-7.53333, 28.66667], "name": "Northwest Africa 2265", "class": "L3.8", "mass": "40", "year": 2001}, {"coordinates": [155.75, -79.68333], "name": "Meteorite Hills 00727", "class": "H6", "mass": "13.24", "year": 2000}, {"coordinates": [57.23795, 21.05172], "name": "Sayh al Uhaymir 154", "class": "H4", "mass": "19.34", "year": 2002}, {"coordinates": [159.75, -79.68333], "name": "Meteorite Hills 001114", "class": "H5", "mass": "56.6", "year": 2000}, {"coordinates": [54.71652, 19.15725], "name": "Dhofar 1421", "class": "H~5", "mass": "110.8", "year": 2001}, {"coordinates": [54.82085, 19.10677], "name": "Dhofar 384", "class": "H5", "mass": "49", "year": 2001}, {"coordinates": [54.71285, 18.89213], "name": "Dhofar 751", "class": "H6", "mass": "1155", "year": 2000}, {"coordinates": [57.31972, 20.99838], "name": "Sayh al Uhaymir 297", "class": "H~5", "mass": "1.6", "year": 2004}, {"coordinates": [75.30056, -72.78194], "name": "Grove Mountains 053630", "class": "L5", "mass": "0.77", "year": 2006}, {"coordinates": [75.31417, -72.935], "name": "Grove Mountains 051523", "class": "Eucrite-mmict", "mass": "0.8", "year": 2006}, {"coordinates": [54.20318, 18.70388], "name": "Dhofar 409", "class": "H5", "mass": "162", "year": 2001}, {"coordinates": [75.29583, -72.78556], "name": "Grove Mountains 021623", "class": "H5", "mass": "0.46", "year": 2003}, {"coordinates": [75.31472, -72.77583], "name": "Grove Mountains 023090", "class": "H5", "mass": "1.16", "year": 2003}, {"coordinates": [57.15368, 21.00345], "name": "Sayh al Uhaymir 407", "class": "H4", "mass": "720.2", "year": 2005}, {"coordinates": [75.28167, -72.78028], "name": "Grove Mountains 022381", "class": "H5", "mass": "0.8", "year": 2003}, {"coordinates": [75.27167, -72.78389], "name": "Grove Mountains 052399", "class": "L6", "mass": "2.77", "year": 2006}, {"coordinates": [160.40639, -72.99], "name": "Frontier Mountain 01069", "class": "H5", "mass": "5.4", "year": 2001}, {"coordinates": [58.41035, 21.16638], "name": "Ramlat al Wahibah 016", "class": "L6", "mass": "115.43", "year": 2006}, {"coordinates": [54.76417, 19.17597], "name": "Dhofar 473", "class": "L6", "mass": "145", "year": 2001}, {"coordinates": [54.38, 18.70667], "name": "Dhofar 518", "class": "H6", "mass": "247", "year": 2000}, {"coordinates": [75.31389, -72.77833], "name": "Grove Mountains 022280", "class": "L6", "mass": "6.38", "year": 2003}, {"coordinates": [160.39972, -72.99472], "name": "Frontier Mountain 01138", "class": "H3", "mass": "4.2", "year": 2001}, {"coordinates": [75.29028, -72.94111], "name": "Grove Mountains 021476", "class": "L6", "mass": "3.38", "year": 2003}, {"coordinates": [54.14167, 18.24333], "name": "Dhofar 014", "class": "LL7", "mass": "414", "year": 2000}, {"coordinates": [56.73, 19.84552], "name": "Jiddat al Harasis 713", "class": "H6", "mass": "153.1", "year": 2011}, {"coordinates": [131.7, -30.5], "name": "Watson 006", "class": "L5", "mass": "53", "year": 2009}, {"coordinates": [54.60083, 18.98567], "name": "Dhofar 247", "class": "H6", "mass": "97.8", "year": 2001}, {"coordinates": [31.47278, 1.345], "name": "Hoima", "class": "H6", "mass": "167.7", "year": 2003}, {"coordinates": [75.28194, -72.7825], "name": "Grove Mountains 022611", "class": "L6", "mass": "1.05", "year": 2003}, {"coordinates": [155.75, -79.68333], "name": "Meteorite Hills 00792", "class": "L5", "mass": "49.59", "year": 2000}, {"coordinates": [57.289, 21.06917], "name": "Sayh al Uhaymir 037", "class": "L6", "mass": "160", "year": 2000}, {"coordinates": [159.75, -79.68333], "name": "Meteorite Hills 00710", "class": "L5", "mass": "16.899999999999999", "year": 2000}, {"coordinates": [159.75, -79.68333], "name": "Meteorite Hills 01083", "class": "Ureilite", "mass": "12.6", "year": 2001}, {"coordinates": [56.41967, 19.97362], "name": "Jiddat al Harasis 266", "class": "Mesosiderite", "mass": "150.1", "year": 2005}, {"coordinates": [54.55, 19.005], "name": "Dhofar 235", "class": "LL5", "mass": "394", "year": 2000}, {"coordinates": [75.31778, -72.78167], "name": "Grove Mountains 051924", "class": "L4", "mass": "73.47", "year": 2006}, {"coordinates": [54.61167, 19.03833], "name": "Dhofar 320", "class": "L6", "mass": "413", "year": 2001}, {"coordinates": [75.20639, -72.9925], "name": "Grove Mountains 020202", "class": "H5", "mass": "0.8", "year": 2003}, {"coordinates": [75.20417, -73.10806], "name": "Grove Mountains 050185", "class": "H6", "mass": "2.25", "year": 2006}, {"coordinates": [57.16427, 20.60342], "name": "Sayh al Uhaymir 292", "class": "H5", "mass": "387", "year": 2004}, {"coordinates": [75.29972, -72.79], "name": "Grove Mountains 021640", "class": "H5", "mass": "0.81", "year": 2003}, {"coordinates": [16.24017, 27.2735], "name": "Dar al Gani 837", "class": "L6", "mass": "113", "year": 2000}, {"coordinates": [54.66127, 19.16365], "name": "Dhofar 996", "class": "LL5", "mass": "2717", "year": 2003}, {"coordinates": [55.18148, 19.5317], "name": "Jiddat al Harasis 522", "class": "H6", "mass": "6", "year": 2008}, {"coordinates": [75.35778, -72.82556], "name": "Grove Mountains 053690", "class": "H4", "mass": "1730", "year": 2006}, {"coordinates": [-68.7, -85.63333], "name": "Pecora Escarpment 02076", "class": "L5", "mass": "96.65", "year": 2002}, {"coordinates": [56.815, 20.68], "name": "Sayh al Uhaymir 313", "class": "H4", "mass": "412", "year": 2004}, {"coordinates": [56.62447, 20.097], "name": "Sayh al Uhaymir 466", "class": "L/LL~5", "mass": "228.3", "year": 2008}, {"coordinates": [54.92333, 19.23139], "name": "Dhofar 987", "class": "H4", "mass": "69.3", "year": 2004}, {"coordinates": [75.32306, -72.77472], "name": "Grove Mountains 022919", "class": "L6", "mass": "8.1", "year": 2003}, {"coordinates": [-112.942, 39.49133], "name": "Greener Reservoir", "class": "H4", "mass": "45", "year": 2004}, {"coordinates": [-7.5, 27.91667], "name": "Northwest Africa 2264", "class": "L6", "mass": "40.200000000000003", "year": 2002}, {"coordinates": [-112.55, 33.91667], "name": "Trilby Wash", "class": "L4", "mass": "846", "year": 2005}, {"coordinates": [-70.53333, -24.85], "name": "El M\u00e9dano 070", "class": "L6", "mass": "51", "year": 2011}, {"coordinates": [75.27083, -72.97667], "name": "Grove Mountains 020158", "class": "L4", "mass": "1101.8", "year": 2003}, {"coordinates": [159.75, -79.68333], "name": "Meteorite Hills 00959", "class": "LL6", "mass": "51.4", "year": 2000}, {"coordinates": [56.82793, 19.46028], "name": "Jiddat al Harasis 096", "class": "L6", "mass": "1853.5", "year": 2002}, {"coordinates": [155.75, -79.68333], "name": "Meteorite Hills 00590", "class": "LL6", "mass": "90.02", "year": 2000}, {"coordinates": [54.195, 18.34167], "name": "Dhofar 189", "class": "H3.8", "mass": "120", "year": 2000}, {"coordinates": [-116.74847, 35.07028], "name": "Coyote Dry Lake 132", "class": "H4", "mass": "17.399999999999999", "year": 2000}, {"coordinates": [54.81028, 19.10593], "name": "Dhofar 387", "class": "L6", "mass": "491", "year": 2001}, {"coordinates": [159.37458, -76.74245], "name": "Allan Hills 09002", "class": "L6", "mass": "71.599999999999994", "year": 2009}, {"coordinates": [75.20639, -72.9925], "name": "Grove Mountains 020221", "class": "H4", "mass": "28.8", "year": 2003}, {"coordinates": [55.72533, 19.72743], "name": "Jiddat al Harasis 334", "class": "L6", "mass": "261.64999999999998", "year": 2006}, {"coordinates": [56.39488, 20.57807], "name": "Ramlat as Sahmah 282", "class": "H3-5", "mass": "132", "year": 2009}, {"coordinates": [160.51167, -72.95167], "name": "Frontier Mountain 01099", "class": "H5-6", "mass": "3.7", "year": 2001}, {"coordinates": [75.34778, -72.77389], "name": "Grove Mountains 022428", "class": "H6", "mass": "0.84", "year": 2003}, {"coordinates": [54.3784, 18.72237], "name": "Dhofar 554", "class": "H5", "mass": "751", "year": 2001}, {"coordinates": [56.22002, 20.3936], "name": "Ramlat as Sahmah 418", "class": "L6", "mass": "28791", "year": 2010}, {"coordinates": [75.2718, -72.7839], "name": "Grove Mountains 052398", "class": "L6", "mass": "4.04", "year": 2006}, {"coordinates": [57.34307, 21.043], "name": "Sayh al Uhaymir 196", "class": "L6", "mass": "407.77", "year": 2002}, {"coordinates": [75.30889, -72.78389], "name": "Grove Mountains 052919", "class": "L5", "mass": "1.46", "year": 2006}, {"coordinates": [75.32, -72.77611], "name": "Grove Mountains 022413", "class": "L5", "mass": "4.31", "year": 2003}, {"coordinates": [155.75, -79.68333], "name": "Meteorite Hills 00551", "class": "LL6", "mass": "58.63", "year": 2000}, {"coordinates": [55.85287, 20.58408], "name": "Ramlat as Sahmah 209", "class": "H5", "mass": "100.47", "year": 2003}, {"coordinates": [75.27944, -72.78139], "name": "Grove Mountains 022675", "class": "H5", "mass": "0.65", "year": 2003}, {"coordinates": [75.28056, -72.7825], "name": "Grove Mountains 022600", "class": "L6 ", "mass": "0.81", "year": 2003}, {"coordinates": [75.3025, -72.77917], "name": "Grove Mountains 054256", "class": "L4", "mass": "0.84", "year": 2006}, {"coordinates": [75.32222, -72.7825], "name": "Grove Mountains 021637", "class": "L6", "mass": "2.18", "year": 2003}, {"coordinates": [-69.88583, -25.4395], "name": "San Juan 052", "class": "L3", "mass": "49", "year": 2009}, {"coordinates": [54.37842, 18.7128], "name": "Dhofar 567", "class": "H6", "mass": "328", "year": 2001}, {"coordinates": [159.75, -79.68333], "name": "Meteorite Hills 001030", "class": "H6", "mass": "20.7", "year": 2000}, {"coordinates": [13.43333, 58.58333], "name": "\u00d6sterplana 044", "class": "Relict OC", "mass": "", "year": 2002}, {"coordinates": [75.3275, -72.77806], "name": "Grove Mountains 021896", "class": "H5", "mass": "0.89", "year": 2003}, {"coordinates": [54.895, 18.945], "name": "Dhofar 720", "class": "H4", "mass": "392", "year": 2000}, {"coordinates": [54.01833, 18.58833], "name": "Dhofar 317", "class": "L5", "mass": "2897", "year": 2001}, {"coordinates": [54.5555, 19.15547], "name": "Dhofar 962", "class": "H4", "mass": "63.5", "year": 2004}, {"coordinates": [75.20917, -73.09806], "name": "Grove Mountains 020008", "class": "H4", "mass": "6.17", "year": 2002}, {"coordinates": [56.54333, 19.50543], "name": "Jiddat al Harasis 650", "class": "H5", "mass": "868", "year": 2010}, {"coordinates": [-70.51667, -24.25], "name": "Caleta el Cobre 017", "class": "H5", "mass": "41", "year": 2010}, {"coordinates": [56.35117, 19.92282], "name": "Jiddat al Harasis 424", "class": "Ureilite", "mass": "160.32", "year": 2007}, {"coordinates": [75.30556, -72.78139], "name": "Grove Mountains 022198", "class": "L6", "mass": "0.66", "year": 2003}, {"coordinates": [-70.53333, -24.85], "name": "El M\u00e9dano 109", "class": "H3", "mass": "13.1", "year": 2011}, {"coordinates": [12.1135, 30.11983], "name": "Hammadah al Hamra 300", "class": "L6", "mass": "893", "year": 2000}, {"coordinates": [155.75, -79.68333], "name": "Meteorite Hills 00619", "class": "H6", "mass": "71.180000000000007", "year": 2000}, {"coordinates": [-79.61667, 43.2], "name": "Grimsby", "class": "H5", "mass": "215", "year": 2009}, {"coordinates": [159.75, -79.68333], "name": "Meteorite Hills 01240", "class": "L5", "mass": "60.3", "year": 2001}, {"coordinates": [159.75, -79.68333], "name": "Meteorite Hills 00460", "class": "H5", "mass": "700.5", "year": 2000}, {"coordinates": [160.5, -84.21667], "name": "MacAlpine Hills 02837", "class": "EL3", "mass": "188.6", "year": 2002}, {"coordinates": [159.75, -79.68333], "name": "Meteorite Hills 01011", "class": "LL5", "mass": "136.6", "year": 2001}, {"coordinates": [-103.93333, 34.21667], "name": "Roosevelt County 106", "class": "L6", "mass": "98.8", "year": 2001}, {"coordinates": [126.61667, -30.31667], "name": "Camel Donga 053", "class": "LL5-6", "mass": "579", "year": 2008}, {"coordinates": [57.29667, 21.06], "name": "Sayh al Uhaymir 322", "class": "H5", "mass": "468", "year": 2005}, {"coordinates": [75.31972, -72.77944], "name": "Grove Mountains 051816", "class": "L5", "mass": "4.1", "year": 2006}, {"coordinates": [13.43333, 58.58333], "name": "\u00d6sterplana 060", "class": "Relict OC", "mass": "0", "year": 2009}, {"coordinates": [75.2464, -72.9839], "name": "Grove Mountains 020918", "class": "L5", "mass": "2.07", "year": 2003}]